generic_temperature_converter/__init__.py
generic_temperature_converter/converter.py
generic_temperature_converter-0.1.3.dist-info/licenses/LICENSE
generic_temperature_converter-0.1.3.dist-info/METADATA
generic_temperature_converter-0.1.3.dist-info/WHEEL
generic_temperature_converter-0.1.3.dist-info/entry_points.txt
generic_temperature_converter-0.1.3.dist-info/top_level.txt
generic_temperature_converter-0.1.3.dist-info/RECORD
