Metadata-Version: 2.4
Name: generic-temperature-converter
Version: 0.1.3
Summary: A simple and generic temperature converter CLI tool for converting between Celsius, Fahrenheit, and Kelvin.
Author-email: Pratik <joshipratik8999@gmail.com>
License: Copyright (c) 2025 Pratik Joshi
Project-URL: Homepage, https://github.com/Pratik8999/build-and-publish-pypi-package
Requires-Python: >=3.7
License-File: LICENSE
Dynamic: license-file
